cy_procedure/__init__.py
cy_procedure/bnc_cli.py
cy_procedure/ok_cli.py
cy_procedure/generic/__init__.py
cy_procedure/generic/spot_fetching.py
cy_procedure/subject/__init__.py
cy_procedure/subject/aims.py
cy_procedure/subject/aip.py
cy_procedure/subject/aips/__init__.py
cy_procedure/subject/aips/aip_base.py
cy_procedure/subject/aips/aip_binance.py
cy_procedure/subject/backtest/__init__.py
cy_procedure/subject/backtest/generic.py
cy_procedure/subject/crawler/__init__.py
cy_procedure/subject/crawler/config_reader.py
cy_procedure/subject/crawler/crawler.py
cy_procedure/subject/exchange/__init__.py
cy_procedure/subject/exchange/binance.py
cy_procedure/subject/exchange/okex.py
cy_procedure/subject/neutral/__init__.py
cy_procedure/subject/neutral/alpha_finder.py
cy_procedure/subject/neutral/functions.py
cy_procedure/subject/neutral/proc/__init__.py
cy_procedure/subject/neutral/proc/binance_swap_neutral.py
cy_procedure/subject/quant/__init__.py
cy_procedure/subject/quant/base.py
cy_procedure/subject/quant/bnc_future.py
cy_procedure/subject/quant/ok_delivery.py
cy_procedure/util/__init__.py
cy_procedure/util/helper.py
cy_procedure/util/logger.py
cy_procedure-0.5.51.dist-info/METADATA
cy_procedure-0.5.51.dist-info/WHEEL
cy_procedure-0.5.51.dist-info/entry_points.txt
cy_procedure-0.5.51.dist-info/top_level.txt
cy_procedure-0.5.51.dist-info/RECORD
