Metadata-Version: 2.1
Name: cy-procedure
Version: 0.5.51
Summary: Procedures based on components/widgets/dao
Home-page: https://github.com/cragod/CYProcedure
Author: CY Gatro
Author-email: cragodn@gmail.com
Keywords: cy_procedure
Classifier: Development Status :: 2 - Pre-Alpha
Classifier: Intended Audience :: Developers
Classifier: Natural Language :: English
Classifier: Programming Language :: Python :: 3
Classifier: Programming Language :: Python :: 3.5
Classifier: Programming Language :: Python :: 3.6
Classifier: Programming Language :: Python :: 3.7
Classifier: Programming Language :: Python :: 3.8
Requires-Python: >=3.5
Requires-Dist: Click (>=7.0)
Requires-Dist: cy-components (>=0.3.11)
Requires-Dist: cy-widgets (>=0.4.29)
Requires-Dist: cy-data-access (>=0.4.23)
Requires-Dist: fracdiff (>=0.0)
